{
    "relayCounter": 1,
    "label": "Region.Utility 1.BRYAN 5",
    "networkLan": "10.58.1225.0",
    "supernetMask": "255.255.255.128",
    "utility": "Utility 1",
    "utility_id": 58,
    "substation": "BRYAN 5",
    "substationNumber": 1225,
    "OTAddress": "10.58.1225.0",
    "OTSubnetMask": "255.255.255.192",
    "OTHosts": [
        "10.58.1225.1",
        "10.58.1225.2",
        "10.58.1225.3",
        "10.58.1225.4",
        "10.58.1225.5",
        "10.58.1225.6",
        "10.58.1225.7",
        "10.58.1225.8",
        "10.58.1225.9",
        "10.58.1225.10",
        "10.58.1225.11",
        "10.58.1225.12",
        "10.58.1225.13",
        "10.58.1225.14",
        "10.58.1225.15",
        "10.58.1225.16",
        "10.58.1225.17",
        "10.58.1225.18",
        "10.58.1225.19",
        "10.58.1225.20",
        "10.58.1225.21",
        "10.58.1225.22",
        "10.58.1225.23",
        "10.58.1225.24",
        "10.58.1225.25",
        "10.58.1225.26",
        "10.58.1225.27",
        "10.58.1225.28",
        "10.58.1225.29",
        "10.58.1225.30",
        "10.58.1225.31",
        "10.58.1225.32",
        "10.58.1225.33",
        "10.58.1225.34",
        "10.58.1225.35",
        "10.58.1225.36",
        "10.58.1225.37",
        "10.58.1225.38",
        "10.58.1225.39",
        "10.58.1225.40",
        "10.58.1225.41",
        "10.58.1225.42",
        "10.58.1225.43",
        "10.58.1225.44",
        "10.58.1225.45",
        "10.58.1225.46",
        "10.58.1225.47",
        "10.58.1225.48",
        "10.58.1225.49",
        "10.58.1225.50",
        "10.58.1225.51",
        "10.58.1225.52",
        "10.58.1225.53",
        "10.58.1225.54",
        "10.58.1225.55",
        "10.58.1225.56",
        "10.58.1225.57",
        "10.58.1225.58",
        "10.58.1225.59",
        "10.58.1225.60",
        "10.58.1225.61",
        "10.58.1225.62"
    ],
    "routeAddress": "10.58.1225.64",
    "routeSubnetMask": "255.255.255.224",
    "routingHosts": [
        "10.58.1225.65",
        "10.58.1225.66",
        "10.58.1225.67",
        "10.58.1225.68",
        "10.58.1225.69",
        "10.58.1225.70",
        "10.58.1225.71",
        "10.58.1225.72",
        "10.58.1225.73",
        "10.58.1225.74",
        "10.58.1225.75",
        "10.58.1225.76",
        "10.58.1225.77",
        "10.58.1225.78",
        "10.58.1225.79",
        "10.58.1225.80",
        "10.58.1225.81",
        "10.58.1225.82",
        "10.58.1225.83",
        "10.58.1225.84",
        "10.58.1225.85",
        "10.58.1225.86",
        "10.58.1225.87",
        "10.58.1225.88",
        "10.58.1225.89",
        "10.58.1225.90",
        "10.58.1225.91",
        "10.58.1225.92",
        "10.58.1225.93",
        "10.58.1225.94"
    ],
    "corporateAddress": "10.58.1225.96",
    "corporateSubnetMask": "255.255.255.224",
    "corporateHosts": [
        "10.58.1225.97",
        "10.58.1225.98",
        "10.58.1225.99",
        "10.58.1225.100",
        "10.58.1225.101",
        "10.58.1225.102",
        "10.58.1225.103",
        "10.58.1225.104",
        "10.58.1225.105",
        "10.58.1225.106",
        "10.58.1225.107",
        "10.58.1225.108",
        "10.58.1225.109",
        "10.58.1225.110",
        "10.58.1225.111",
        "10.58.1225.112",
        "10.58.1225.113",
        "10.58.1225.114",
        "10.58.1225.115",
        "10.58.1225.116",
        "10.58.1225.117",
        "10.58.1225.118",
        "10.58.1225.119",
        "10.58.1225.120",
        "10.58.1225.121",
        "10.58.1225.122",
        "10.58.1225.123",
        "10.58.1225.124",
        "10.58.1225.125"
    ],
    "latitude": 30.743,
    "longitude": -96.548,
    "nodes": [
        {
            "utility": "Utility 1",
            "adminIP": "10.58.1225.97",
            "ipAddress": "10.58.1225.96",
            "subnetMask": "255.255.255.224",
            "vlan": "Corporate",
            "substation": "BRYAN 5",
            "label": "Utility 1.BRYAN 5..Firewall 1225",
            "compromised": false,
            "acls": {
                "acl0": [
                    {
                        "description": "Allow DNP3",
                        "source": "10.52.1.",
                        "destination": "10.52.1.",
                        "port": "20000",
                        "transportLayer": "TCP",
                        "action": "allow"
                    }
                ],
                "acl1": [
                    {
                        "description": "Allow HTTPS",
                        "source": "10.52.1.",
                        "destination": "10.52.1.",
                        "port": "443",
                        "transportLayer": "TCP",
                        "action": "allow"
                    }
                ],
                "acl2": [
                    {
                        "description": "Block ICCP",
                        "source": "all",
                        "destination": "all",
                        "port": "102",
                        "transportLayer": "TCP",
                        "action": "block"
                    }
                ],
                "acl3": [
                    {
                        "description": "Block SQL",
                        "source": "all",
                        "destination": "all",
                        "port": "3306",
                        "transportLayer": "TCP",
                        "action": "block"
                    }
                ]
            },
            "interfaces": [],
            "Latitude": 30.743,
            "Longitude": -96.548
        },
        {
            "utility": "Utility 1",
            "adminIP": "10.58.1225.98",
            "ipAddress": "10.58.1225.96",
            "subnetMask": "255.255.255.224",
            "vlan": "Corporate",
            "substation": "BRYAN 5",
            "label": "Utility 1.BRYAN 5..Router 1225",
            "compromised": false,
            "interfaces": [],
            "routingTable": {}
        },
        {
            "utility": "Utility 1",
            "adminIP": "10.58.1225.1",
            "ipAddress": "10.58.1225.0",
            "subnetMask": "255.255.255.192",
            "vlan": "OT",
            "substation": "BRYAN 5",
            "label": "Utility 1.BRYAN 5.OT.Switch 2449",
            "compromised": false,
            "arpTable": []
        },
        {
            "utility": "Utility 1",
            "adminIP": "10.58.1225.99",
            "ipAddress": "10.58.1225.96",
            "subnetMask": "255.255.255.224",
            "vlan": "Corporate",
            "substation": "BRYAN 5",
            "label": "Utility 1.BRYAN 5.Corporate.Switch 2450",
            "compromised": false,
            "arpTable": []
        },
        {
            "utility": "Utility 1",
            "adminIP": "10.58.1225.3",
            "ipAddress": "10.58.1225.0",
            "subnetMask": "255.255.255.192",
            "vlan": "OT",
            "substation": "BRYAN 5",
            "label": "Utility 1.BRYAN 5..Relay 101",
            "compromised": false,
            "breakers": [],
            "busNumber": "",
            "relayType": "Line",
            "relaySubType": "OC",
            "protocol": {}
        },
        {
            "utility": "Utility 1",
            "adminIP": "10.58.1225.2",
            "ipAddress": "10.58.1225.0",
            "subnetMask": "255.255.255.192",
            "vlan": "OT",
            "substation": "BRYAN 5",
            "label": "Utility 1.BRYAN 5..RC 1225",
            "compromised": false,
            "relayIPlist": [
                "10.58.1225.3"
            ],
            "protocol": {
                "DNP3": [
                    {
                        "port": "20000",
                        "transportLayer": "TCP"
                    }
                ]
            }
        },
        {
            "utility": "Utility 1",
            "adminIP": "10.58.1225.100",
            "ipAddress": "10.58.1225.96",
            "subnetMask": "255.255.255.224",
            "vlan": "Corporate",
            "substation": "BRYAN 5",
            "label": "Utility 1.BRYAN 5..Host 2449",
            "compromised": false,
            "protocol": {
                "HTTPS": [
                    {
                        "port": "443",
                        "transportLayer": "TCP"
                    }
                ]
            }
        },
        {
            "utility": "Utility 1",
            "adminIP": "10.58.1225.100",
            "ipAddress": "10.58.1225.96",
            "subnetMask": "255.255.255.224",
            "vlan": "Corporate",
            "substation": "BRYAN 5",
            "label": "Utility 1.BRYAN 5..Host 2450",
            "compromised": false,
            "protocol": {
                "HTTPS": [
                    {
                        "port": "443",
                        "transportLayer": "TCP"
                    }
                ]
            }
        },
        {
            "utility": "Utility 1",
            "adminIP": "10.58.1225.100",
            "ipAddress": "10.58.1225.96",
            "subnetMask": "255.255.255.224",
            "vlan": "Corporate",
            "substation": "BRYAN 5",
            "label": "Utility 1.BRYAN 5..LocalDatabase 2449",
            "compromised": false,
            "protocol": {
                "SQL": [
                    {
                        "port": "3306",
                        "transportLayer": "TCP"
                    }
                ]
            }
        },
        {
            "utility": "Utility 1",
            "adminIP": "10.58.1225.100",
            "ipAddress": "10.58.1225.96",
            "subnetMask": "255.255.255.224",
            "vlan": "Corporate",
            "substation": "BRYAN 5",
            "label": "Utility 1.BRYAN 5..LocalWebServer 2450",
            "compromised": false,
            "protocol": {
                "HTTPS": [
                    {
                        "port": "443",
                        "transportLayer": "TCP"
                    }
                ]
            }
        },
        {
            "utility": "Utility 1",
            "adminIP": "10.58.1225.101",
            "ipAddress": "10.58.1225.96",
            "subnetMask": "255.255.255.224",
            "vlan": "Corporate",
            "substation": "BRYAN 5",
            "label": "Utility 1.BRYAN 5..hmi 2449",
            "compromised": false,
            "protocol": {
                "HTTPS": [
                    {
                        "port": "443",
                        "transportLayer": "TCP"
                    }
                ]
            }
        },
        {
            "utility": "Utility 1",
            "adminIP": "10.58.1225.100",
            "ipAddress": "10.58.1225.96",
            "subnetMask": "255.255.255.224",
            "vlan": "Corporate",
            "substation": "BRYAN 5",
            "label": "Utility 1.BRYAN 5..outstation 2450",
            "compromised": false,
            "protocol": {
                "DNP3": [
                    {
                        "port": "20000",
                        "transportLayer": "TCP"
                    }
                ],
                "SQL": [
                    {
                        "port": "3306",
                        "transportLayer": "TCP"
                    }
                ]
            }
        }
    ],
    "links": [
        {
            "source": "Utility 1.BRYAN 5..RC 1225",
            "destination": "Utility 1.BRYAN 5..Relay 101",
            "link_type": "Ethernet",
            "bandwidth": 10.0,
            "distance": 10.0,
            "compromised": false
        },
        {
            "source": "Utility 1.BRYAN 5..Router 1225",
            "destination": "Utility 1.BRYAN 5..Firewall 1225",
            "link_type": "Ethernet",
            "bandwidth": 10.0,
            "distance": 10.0,
            "compromised": false
        },
        {
            "source": "Utility 1.BRYAN 5..Firewall 1225",
            "destination": "Utility 1.BRYAN 5.OT.Switch 2449",
            "link_type": "Ethernet",
            "bandwidth": 10.0,
            "distance": 10.0,
            "compromised": false
        },
        {
            "source": "Utility 1.BRYAN 5.OT.Switch 2449",
            "destination": "Utility 1.BRYAN 5..RC 1225",
            "link_type": "Ethernet",
            "bandwidth": 10.0,
            "distance": 10.0,
            "compromised": false
        },
        {
            "source": "Utility 1.BRYAN 5..Firewall 1225",
            "destination": "Utility 1.BRYAN 5.Corporate.Switch 2450",
            "link_type": "Ethernet",
            "bandwidth": 10.0,
            "distance": 10.0,
            "compromised": false
        },
        {
            "source": "Utility 1.BRYAN 5.Corporate.Switch 2450",
            "destination": "Utility 1.BRYAN 5..Host 2449",
            "link_type": "Ethernet",
            "bandwidth": 10.0,
            "distance": 10.0,
            "compromised": false
        },
        {
            "source": "Utility 1.BRYAN 5.Corporate.Switch 2450",
            "destination": "Utility 1.BRYAN 5..Host 2450",
            "link_type": "Ethernet",
            "bandwidth": 10.0,
            "distance": 10.0,
            "compromised": false
        },
        {
            "source": "Utility 1.BRYAN 5.Corporate.Switch 2450",
            "destination": "Utility 1.BRYAN 5..LocalDatabase 2449",
            "link_type": "Ethernet",
            "bandwidth": 10.0,
            "distance": 10.0,
            "compromised": false
        },
        {
            "source": "Utility 1.BRYAN 5.Corporate.Switch 2450",
            "destination": "Utility 1.BRYAN 5..LocalWebServer 2450",
            "link_type": "Ethernet",
            "bandwidth": 10.0,
            "distance": 10.0,
            "compromised": false
        }
    ],
    "switches": [
        {
            "utility": "Utility 1",
            "adminIP": "10.58.1225.1",
            "ipAddress": "10.58.1225.0",
            "subnetMask": "255.255.255.192",
            "vlan": "OT",
            "substation": "BRYAN 5",
            "label": "Utility 1.BRYAN 5.OT.Switch 2449",
            "compromised": false,
            "arpTable": []
        }
    ],
    "rcs": [
        {
            "utility": "Utility 1",
            "adminIP": "10.58.1225.2",
            "ipAddress": "10.58.1225.0",
            "subnetMask": "255.255.255.192",
            "vlan": "OT",
            "substation": "BRYAN 5",
            "label": "Utility 1.BRYAN 5..RC 1225",
            "compromised": false,
            "relayIPlist": [
                "10.58.1225.3"
            ],
            "protocol": {
                "DNP3": [
                    {
                        "port": "20000",
                        "transportLayer": "TCP"
                    }
                ]
            }
        }
    ],
    "substationFirewall": [
        {
            "utility": "Utility 1",
            "adminIP": "10.58.1225.97",
            "ipAddress": "10.58.1225.96",
            "subnetMask": "255.255.255.224",
            "vlan": "Corporate",
            "substation": "BRYAN 5",
            "label": "Utility 1.BRYAN 5..Firewall 1225",
            "compromised": false,
            "acls": {
                "acl0": [
                    {
                        "description": "Allow DNP3",
                        "source": "10.52.1.",
                        "destination": "10.52.1.",
                        "port": "20000",
                        "transportLayer": "TCP",
                        "action": "allow"
                    }
                ],
                "acl1": [
                    {
                        "description": "Allow HTTPS",
                        "source": "10.52.1.",
                        "destination": "10.52.1.",
                        "port": "443",
                        "transportLayer": "TCP",
                        "action": "allow"
                    }
                ],
                "acl2": [
                    {
                        "description": "Block ICCP",
                        "source": "all",
                        "destination": "all",
                        "port": "102",
                        "transportLayer": "TCP",
                        "action": "block"
                    }
                ],
                "acl3": [
                    {
                        "description": "Block SQL",
                        "source": "all",
                        "destination": "all",
                        "port": "3306",
                        "transportLayer": "TCP",
                        "action": "block"
                    }
                ]
            },
            "interfaces": [],
            "Latitude": 30.743,
            "Longitude": -96.548
        }
    ],
    "substationRouter": [
        {
            "utility": "Utility 1",
            "adminIP": "10.58.1225.98",
            "ipAddress": "10.58.1225.96",
            "subnetMask": "255.255.255.224",
            "vlan": "Corporate",
            "substation": "BRYAN 5",
            "label": "Utility 1.BRYAN 5..Router 1225",
            "compromised": false,
            "interfaces": [],
            "routingTable": {}
        }
    ],
    "substationSwitch": [
        {
            "utility": "Utility 1",
            "adminIP": "10.58.1225.1",
            "ipAddress": "10.58.1225.0",
            "subnetMask": "255.255.255.192",
            "vlan": "OT",
            "substation": "BRYAN 5",
            "label": "Utility 1.BRYAN 5.OT.Switch 2449",
            "compromised": false,
            "arpTable": []
        }
    ],
    "substationrelayController": [
        {
            "utility": "Utility 1",
            "adminIP": "10.58.1225.2",
            "ipAddress": "10.58.1225.0",
            "subnetMask": "255.255.255.192",
            "vlan": "OT",
            "substation": "BRYAN 5",
            "label": "Utility 1.BRYAN 5..RC 1225",
            "compromised": false,
            "relayIPlist": [
                "10.58.1225.3"
            ],
            "protocol": {
                "DNP3": [
                    {
                        "port": "20000",
                        "transportLayer": "TCP"
                    }
                ]
            }
        }
    ],
    "compromised": false,
    "type": "transmission"
}